{
     "status_code": 200,
     "message": "Success",
     "data": [
          {
               "type": "landscape_slide",
               "banner_path": "https://wallpaperaccess.com/full/1940042.jpg",
               "link": "https://github.com/IJlnflhbrzDev"
          },
          {
               "type": "landscape_slide",
               "banner_path": "https://wallpaperaccess.com/full/1940042.jpg",
               "link": "https://github.com/IJlnflhbrzDev"
          },
          {
               "type": "landscape_slide",
               "banner_path": "https://wallpaperaccess.com/full/1940042.jpg",
               "link": "https://github.com/IJlnflhbrzDev"
          },
          {
               "type": "square",
               "banner_path": "https://bdsgp.my.id/img/800/bw5d48ohbw5fisnofm_3/f9nFomQj9GvguMf9oeR0bBwGj7ZB6S5quW1vcxjLg.webp",
               "link": "https://github.com/IJlnflhbrzDev"
          },
          {
               "type": "square",
               "banner_path": "https://images.unsplash.com/photo-1468418143278-41595b1a4c89?ixlib=rb-1.2.1&ixid=MnwxMjA3fDB8MHxzZWFyY2h8Mnx8ZmxhdGV8ZW58MHwwfDB8fA%3D%3D&auto=format&fit=crop&w=500&q=60",
               "link": "https://github.com/IJlnflhbrzDev"
          },
          {
               "type": "landscape_small",
               "banner_path": "https://images.unsplash.com/photo-1468418143278-41595b1a4c89?ixlib=rb-1.2.1&ixid=MnwxMjA3fDB8MHxzZWFyY2h8Mnx8ZmxhdGV8ZW58MHwwfDB8fA%3D%3D&auto=format&fit=crop&w=500&q=60",
               "link": "https://github.com/IJlnflhbrzDev"
          },
          {
               "type": "potrait",
               "banner_path": "https://bdsgp.my.id/img/800/bw5d48ohbw5fisnofm_3/f9nFomQj9GvguMf9oeR0bBwGj7ZB6S5quW1vcxjLg.webp",
               "link": "https://github.com/IJlnflhbrzDev"
          },
          {
               "type": "potrait",
               "banner_path": "https://bdsgp.my.id/img/800/bw5d48ohbw5fisnofm_3/f9nFomQj9GvguMf9oeR0bBwGj7ZB6S5quW1vcxjLg.webp",
               "link": "https://github.com/IJlnflhbrzDev"
          },
          {
               "type": "potrait",
               "banner_path": "https://bdsgp.my.id/img/800/bw5d48ohbw5fisnofm_3/f9nFomQj9GvguMf9oeR0bBwGj7ZB6S5quW1vcxjLg.webp",
               "link": "https://github.com/IJlnflhbrzDev"
          },
          {
               "type": "potrait",
               "banner_path": "https://bdsgp.my.id/img/800/bw5d48ohbw5fisnofm_3/f9nFomQj9GvguMf9oeR0bBwGj7ZB6S5quW1vcxjLg.webp",
               "link": "https://github.com/IJlnflhbrzDev"
          }
     ]
}